fluent/__about__.py
fluent/__init__.py
fluent/asynchandler.py
fluent/asyncsender.py
fluent/event.py
fluent/handler.py
fluent/sender.py
fluent_logger-0.11.0.dist-info/METADATA
fluent_logger-0.11.0.dist-info/WHEEL
fluent_logger-0.11.0.dist-info/licenses/COPYING
fluent_logger-0.11.0.dist-info/RECORD
