Metadata-Version: 2.1
Name: fluent-logger
Version: 0.11.0
Summary: A Python logging handler for Fluentd event collector
Project-URL: Download, https://pypi.org/project/fluent-logger/
Project-URL: Homepage, https://github.com/fluent/fluent-logger-python
Author-email: Kazuki Ohta <kazuki.ohta@gmail.com>
Maintainer-email: Arcadiy Ivanov <arcadiy@ivanov.biz>, Inada Naoki <songofacandy@gmail.com>
License: Copyright (C) 2011 FURUHASHI Sadayuki
License-File: COPYING
Classifier: Development Status :: 5 - Production/Stable
Classifier: Intended Audience :: Developers
Classifier: Programming Language :: Python :: 3
Classifier: Programming Language :: Python :: 3.7
Classifier: Programming Language :: Python :: 3.8
Classifier: Programming Language :: Python :: 3.9
Classifier: Programming Language :: Python :: 3.10
Classifier: Programming Language :: Python :: 3.11
Classifier: Programming Language :: Python :: 3.12
Classifier: Programming Language :: Python :: Implementation :: CPython
Classifier: Programming Language :: Python :: Implementation :: PyPy
Classifier: Topic :: System :: Logging
Requires-Python: >=3.7
Requires-Dist: msgpack>=1.0
